spot/__init__.py
spot/auto_spot.py
spot/diff_file_size.py
spot/spottool.py
spot/subj_clustering.py
spot/verify_files.py
spot/wrapper.py
spottool-0.2.dist-info/LICENSE
spottool-0.2.dist-info/METADATA
spottool-0.2.dist-info/WHEEL
spottool-0.2.dist-info/entry_points.txt
spottool-0.2.dist-info/top_level.txt
spottool-0.2.dist-info/RECORD
