Metadata-Version: 2.1
Name: spottool
Version: 0.2
Summary: A set of tools to evaluate the reproducibility of computations 
Home-page: https://github.com/big-data-lab-team/spot
Author: Big Data Infrastructures for Neuroinformatics lab
Author-email: UNKNOWN
License: MIT
Platform: UNKNOWN
Classifier: Programming Language :: Python
Classifier: Programming Language :: Python :: Implementation :: PyPy
Classifier: License :: OSI Approved :: MIT License
Classifier: Topic :: Software Development :: Libraries :: Python Modules
Classifier: Operating System :: OS Independent
Classifier: Natural Language :: English
Requires-Dist: numpy
Requires-Dist: pandas
Requires-Dist: boutiques
Requires-Dist: docker
Requires-Dist: zss
Requires-Dist: scipy
Requires-Dist: sklearn
